{
  "apple_music_id": "301631355",
  "apple_music_url": "https://music.apple.com/gb/artist/hurray-for-the-riff-raff/301631355",
  "biography": "Hurray for the Riff Raff is an Americana band from New Orleans, Louisiana. It was formed by Alynda Segarra, a Puerto Rican singer-songwriter from the Bronx, New York, after they had moved to New Orleans in 2007.\n\nAfter leaving home at an early age to travel the country, Segarra eventually settled in New Orleans where they began to perform and record with a revolving cast of musicians.  They released two records (2008's It Don't Mean I Don't Love You and 2010's Young Blood Blues) mostly consisting of delicate folk and country songs.  In 2011, the UK record label Loose Music (Felice Brothers, Dawes, Deer Tick), released Hurray for the Riff Raff, an album that collected the best songs from those records.  The Times of London named Hurray for the Riff Raff one of the Top Ten Albums of 2011.  Phil Alexander, the Editor-in-Chief of Mojo Magazine, raved that they “have immense potential and seductive power” and named them second best band at SXSW 2011.\n\nBack in the States, Alynda met up with a young honky-tonk band called the Tumbleweeds, just as they began to expand they musical palette to include rock n roll, pop, and soul.  In the tradition of Bob Dylan with Band and Neil Young with Crazy Horse, Alynda recruited the Tumbleweeds to be their touring band, drastically altering the sound of Hurray for the Riff Raff.\n\nLook Out Mama is the result of almost two years of Alynda and the Tumbleweeds criss-crossing the USA, playing over 100 shows in small bars and clubs.  Recorded in Nashville by producer Andrija Tokic (Alabama Shakes), Look Out Mama is an exploration of classic American music as interpreted by Alynda lee Segarra.  From the Swamp Pop of \"Little Black Star\" to the Classic Country of \"Look Out Mama\", to the Psychedelia of “Ode to John and Yoko” and even the Surf-Rock of “Lake of Fire”, Look Out Mama covers a wide array of musical ground, with every song unified by Alynda’s soulful vocals and expert songwriting. <a href=\"https://www.last.fm/music/Hurray+For+The+Riff+Raff\">Read more on Last.fm</a>. User-contributed text is available under the Creative Commons By-SA License; additional terms may apply.",
  "country": null,
  "created_at": "2025-07-05T17:23:16.287580",
  "discogs_id": "1819160",
  "discogs_url": "https://www.discogs.com/artist/1819160-Hurray-For-The-Riff-Raff",
  "followers": 142231,
  "formed_date": null,
  "genres": [
    "Alternative",
    "americana",
    "alt country",
    "folk",
    "blues",
    "seen live",
    "New Orleans"
  ],
  "id": "hurray-for-the-riff-raff-1751732599",
  "images": [
    {
      "height": 2000,
      "type": "apple_music_artist",
      "url": "https://is1-ssl.mzstatic.com/image/thumb/AMCArtistImages126/v4/7e/ba/7a/7eba7a5b-be51-516f-a4eb-57b178d218ae/dad82855-e583-4d3c-8a88-ddcea5259c87_ami-identity-6254dad098a5d20354b28653dc5f43b8-2023-11-09T14-39-36.634Z_cropped.png/2000x2000bb.jpg",
      "width": 2000
    },
    {
      "height": 640,
      "type": "spotify_artist",
      "url": "https://i.scdn.co/image/ab6761610000e5eb057068ad79970a943dc50686",
      "width": 640
    },
    {
      "height": 320,
      "type": "spotify_artist",
      "url": "https://i.scdn.co/image/ab67616100005174057068ad79970a943dc50686",
      "width": 320
    },
    {
      "height": 160,
      "type": "spotify_artist",
      "url": "https://i.scdn.co/image/ab6761610000f178057068ad79970a943dc50686",
      "width": 160
    },
    {
      "height": null,
      "type": "lastfm_artist_small",
      "url": "https://lastfm.freetls.fastly.net/i/u/34s/2a96cbd8b46e442fc41c2b86b821562f.png",
      "width": null
    },
    {
      "height": null,
      "type": "lastfm_artist_medium",
      "url": "https://lastfm.freetls.fastly.net/i/u/64s/2a96cbd8b46e442fc41c2b86b821562f.png",
      "width": null
    },
    {
      "height": null,
      "type": "lastfm_artist_large",
      "url": "https://lastfm.freetls.fastly.net/i/u/174s/2a96cbd8b46e442fc41c2b86b821562f.png",
      "width": null
    },
    {
      "height": null,
      "type": "lastfm_artist_extralarge",
      "url": "https://lastfm.freetls.fastly.net/i/u/300x300/2a96cbd8b46e442fc41c2b86b821562f.png",
      "width": null
    },
    {
      "height": null,
      "type": "lastfm_artist_mega",
      "url": "https://lastfm.freetls.fastly.net/i/u/300x300/2a96cbd8b46e442fc41c2b86b821562f.png",
      "width": null
    },
    {
      "height": null,
      "type": "lastfm_artist_",
      "url": "https://lastfm.freetls.fastly.net/i/u/300x300/2a96cbd8b46e442fc41c2b86b821562f.png",
      "width": null
    },
    {
      "height": null,
      "type": "discogs_artist_primary",
      "url": "https://i.discogs.com/TwF5yCxBy57M5AyVtItus9VUCO3ncpCYa3uxvVGEYZk/rs:fit/g:sm/q:90/h:474/w:474/czM6Ly9kaXNjb2dz/LWRhdGFiYXNlLWlt/YWdlcy9BLTE4MTkx/NjAtMTYxOTYyODE1/OC0zODI5LmpwZWc.jpeg",
      "width": null
    },
    {
      "height": null,
      "type": "discogs_artist_thumb",
      "url": "https://i.discogs.com/xaIwCbIQL75hJgXgdVZZiX1gtWGyZ8fLw-TSW3ddPwI/rs:fit/g:sm/q:40/h:150/w:150/czM6Ly9kaXNjb2dz/LWRhdGFiYXNlLWlt/YWdlcy9BLTE4MTkx/NjAtMTYxOTYyODE1/OC0zODI5LmpwZWc.jpeg",
      "width": null
    }
  ],
  "lastfm_mbid": "b053efc9-e8ea-474a-981f-a3c6fffcc694",
  "lastfm_url": "https://www.last.fm/music/Hurray+For+The+Riff+Raff",
  "local_images": {
    "hi-res": "../public/artist/hurray-for-the-riff-raff/hurray-for-the-riff-raff-hi-res.jpg",
    "medium": "../public/artist/hurray-for-the-riff-raff/hurray-for-the-riff-raff-medium.jpg",
    "small": "../public/artist/hurray-for-the-riff-raff/hurray-for-the-riff-raff-small.jpg"
  },
  "name": "Hurray For The Riff Raff",
  "popularity": 49,
  "services": {
    "apple_music": {
      "artwork_url": "https://is1-ssl.mzstatic.com/image/thumb/AMCArtistImages126/v4/7e/ba/7a/7eba7a5b-be51-516f-a4eb-57b178d218ae/dad82855-e583-4d3c-8a88-ddcea5259c87_ami-identity-6254dad098a5d20354b28653dc5f43b8-2023-11-09T14-39-36.634Z_cropped.png/2000x2000bb.jpg",
      "editorial_notes": null,
      "genres": [
        "Alternative"
      ],
      "id": "301631355",
      "name": "Hurray for the Riff Raff",
      "origin": "",
      "url": "https://music.apple.com/gb/artist/hurray-for-the-riff-raff/301631355"
    },
    "discogs": {
      "cover_image": "https://i.discogs.com/TwF5yCxBy57M5AyVtItus9VUCO3ncpCYa3uxvVGEYZk/rs:fit/g:sm/q:90/h:474/w:474/czM6Ly9kaXNjb2dz/LWRhdGFiYXNlLWlt/YWdlcy9BLTE4MTkx/NjAtMTYxOTYyODE1/OC0zODI5LmpwZWc.jpeg",
      "fetch_timestamp": "2025-07-06T13:50:00Z",
      "fetched_externally": true,
      "id": "1819160",
      "images": [
        {
          "height": 474,
          "resource_url": "https://i.discogs.com/TwF5yCxBy57M5AyVtItus9VUCO3ncpCYa3uxvVGEYZk/rs:fit/g:sm/q:90/h:474/w:474/czM6Ly9kaXNjb2dz/LWRhdGFiYXNlLWlt/YWdlcy9BLTE4MTkx/NjAtMTYxOTYyODE1/OC0zODI5LmpwZWc.jpeg",
          "type": "primary",
          "uri": "https://i.discogs.com/TwF5yCxBy57M5AyVtItus9VUCO3ncpCYa3uxvVGEYZk/rs:fit/g:sm/q:90/h:474/w:474/czM6Ly9kaXNjb2dz/LWRhdGFiYXNlLWlt/YWdlcy9BLTE4MTkx/NjAtMTYxOTYyODE1/OC0zODI5LmpwZWc.jpeg",
          "uri150": "https://i.discogs.com/xaIwCbIQL75hJgXgdVZZiX1gtWGyZ8fLw-TSW3ddPwI/rs:fit/g:sm/q:40/h:150/w:150/czM6Ly9kaXNjb2dz/LWRhdGFiYXNlLWlt/YWdlcy9BLTE4MTkx/NjAtMTYxOTYyODE1/OC0zODI5LmpwZWc.jpeg",
          "width": 474
        },
        {
          "height": 267,
          "resource_url": "https://i.discogs.com/0bu4yie6F-1K4xhAcJ8hyIzn8STxvZCh5rgff5qdoxY/rs:fit/g:sm/q:90/h:267/w:490/czM6Ly9kaXNjb2dz/LWRhdGFiYXNlLWlt/YWdlcy9BLTE4MTkx/NjAtMTM5MTczMTYx/OC01NjE5LmpwZWc.jpeg",
          "type": "secondary",
          "uri": "https://i.discogs.com/0bu4yie6F-1K4xhAcJ8hyIzn8STxvZCh5rgff5qdoxY/rs:fit/g:sm/q:90/h:267/w:490/czM6Ly9kaXNjb2dz/LWRhdGFiYXNlLWlt/YWdlcy9BLTE4MTkx/NjAtMTM5MTczMTYx/OC01NjE5LmpwZWc.jpeg",
          "uri150": "https://i.discogs.com/f43mcVb9iPyyeE-6jtE6EZB5DHjYiU6vqGcXU6gm8ps/rs:fit/g:sm/q:40/h:150/w:150/czM6Ly9kaXNjb2dz/LWRhdGFiYXNlLWlt/YWdlcy9BLTE4MTkx/NjAtMTM5MTczMTYx/OC01NjE5LmpwZWc.jpeg",
          "width": 490
        },
        {
          "height": 626,
          "resource_url": "https://i.discogs.com/YlUaBR7auoJzwlnAy8Fhz3RcV-LAF58Mow8Q2wKktiw/rs:fit/g:sm/q:90/h:626/w:600/czM6Ly9kaXNjb2dz/LWRhdGFiYXNlLWlt/YWdlcy9BLTE4MTkx/NjAtMTYxOTYyODE1/Ni03MjY3LmpwZWc.jpeg",
          "type": "secondary",
          "uri": "https://i.discogs.com/YlUaBR7auoJzwlnAy8Fhz3RcV-LAF58Mow8Q2wKktiw/rs:fit/g:sm/q:90/h:626/w:600/czM6Ly9kaXNjb2dz/LWRhdGFiYXNlLWlt/YWdlcy9BLTE4MTkx/NjAtMTYxOTYyODE1/Ni03MjY3LmpwZWc.jpeg",
          "uri150": "https://i.discogs.com/bgjYABLgYYKNCEOz9L9QxWR5I-qKQBSlElQhP7d7f0o/rs:fit/g:sm/q:40/h:150/w:150/czM6Ly9kaXNjb2dz/LWRhdGFiYXNlLWlt/YWdlcy9BLTE4MTkx/NjAtMTYxOTYyODE1/Ni03MjY3LmpwZWc.jpeg",
          "width": 600
        },
        {
          "height": 600,
          "resource_url": "https://i.discogs.com/I5krxShFuwbOMZ4XKCxf0VsNKe_AIejMeSTdYgnocqA/rs:fit/g:sm/q:90/h:600/w:600/czM6Ly9kaXNjb2dz/LWRhdGFiYXNlLWlt/YWdlcy9BLTE4MTkx/NjAtMTYxOTYyODE1/OS05OTY0LmpwZWc.jpeg",
          "type": "secondary",
          "uri": "https://i.discogs.com/I5krxShFuwbOMZ4XKCxf0VsNKe_AIejMeSTdYgnocqA/rs:fit/g:sm/q:90/h:600/w:600/czM6Ly9kaXNjb2dz/LWRhdGFiYXNlLWlt/YWdlcy9BLTE4MTkx/NjAtMTYxOTYyODE1/OS05OTY0LmpwZWc.jpeg",
          "uri150": "https://i.discogs.com/5N7_g3ZkGGOK9e76PZOgQYMXjryJWOWsdMZ0n0JgyVg/rs:fit/g:sm/q:40/h:150/w:150/czM6Ly9kaXNjb2dz/LWRhdGFiYXNlLWlt/YWdlcy9BLTE4MTkx/NjAtMTYxOTYyODE1/OS05OTY0LmpwZWc.jpeg",
          "width": 600
        },
        {
          "height": 336,
          "resource_url": "https://i.discogs.com/7Lr6WXrOEFx4odBsxwTU9rFtmATvD84n1NIwXUj-9jk/rs:fit/g:sm/q:90/h:336/w:600/czM6Ly9kaXNjb2dz/LWRhdGFiYXNlLWlt/YWdlcy9BLTE4MTkx/NjAtMTYxOTYyODE2/MC0xNzk2LmpwZWc.jpeg",
          "type": "secondary",
          "uri": "https://i.discogs.com/7Lr6WXrOEFx4odBsxwTU9rFtmATvD84n1NIwXUj-9jk/rs:fit/g:sm/q:90/h:336/w:600/czM6Ly9kaXNjb2dz/LWRhdGFiYXNlLWlt/YWdlcy9BLTE4MTkx/NjAtMTYxOTYyODE2/MC0xNzk2LmpwZWc.jpeg",
          "uri150": "https://i.discogs.com/4Wvez4rZ5KR7Yej4vQV7AltsYpiqmMkkIDuqa9vbqoY/rs:fit/g:sm/q:40/h:150/w:150/czM6Ly9kaXNjb2dz/LWRhdGFiYXNlLWlt/YWdlcy9BLTE4MTkx/NjAtMTYxOTYyODE2/MC0xNzk2LmpwZWc.jpeg",
          "width": 600
        }
      ],
      "members": [
        {
          "active": false,
          "id": 1588103,
          "name": "Walt McClements",
          "resource_url": "https://api.discogs.com/artists/1588103",
          "thumbnail_url": ""
        },
        {
          "active": true,
          "id": 1984171,
          "name": "Dan Cutler",
          "resource_url": "https://api.discogs.com/artists/1984171",
          "thumbnail_url": "https://i.discogs.com/gB4edjl5ikO42sl5r85Ft5XLBcVPuEoGKOVX5HLog7o/rs:fit/g:sm/q:40/h:600/w:400/czM6Ly9kaXNjb2dz/LWRhdGFiYXNlLWlt/YWdlcy9BLTE5ODQx/NzEtMTQzNTUwMjQw/OC03MjU3LmpwZWc.jpeg"
        },
        {
          "active": true,
          "id": 2260277,
          "name": "Casey McAllister",
          "resource_url": "https://api.discogs.com/artists/2260277",
          "thumbnail_url": "https://i.discogs.com/6nuMggGQKKyUGmaynvuvjHV0LKJJB546Eq8dGj6nOxs/rs:fit/g:sm/q:40/h:399/w:600/czM6Ly9kaXNjb2dz/LWRhdGFiYXNlLWlt/YWdlcy9BLTIyNjAy/NzctMTU4ODg4MDk0/MS05NDg0LmpwZWc.jpeg"
        },
        {
          "active": true,
          "id": 2581847,
          "name": "Alynda Lee Segarra",
          "resource_url": "https://api.discogs.com/artists/2581847",
          "thumbnail_url": "https://i.discogs.com/SvzTL5QhEr5WIFQEhPpOW2YpahtnN-7y3Bm8h3K7qVY/rs:fit/g:sm/q:40/h:347/w:304/czM6Ly9kaXNjb2dz/LWRhdGFiYXNlLWlt/YWdlcy9BLTI1ODE4/NDctMTY1NDAxMDEz/OC03MDAxLmpwZWc.jpeg"
        },
        {
          "active": true,
          "id": 3690925,
          "name": "Yosi Perlstein",
          "resource_url": "https://api.discogs.com/artists/3690925",
          "thumbnail_url": "https://i.discogs.com/frqZRymcdFy4W8MRlbatCrCVfMACH9TomBvdWv-BqLQ/rs:fit/g:sm/q:40/h:400/w:600/czM6Ly9kaXNjb2dz/LWRhdGFiYXNlLWlt/YWdlcy9BLTM2OTA5/MjUtMTQzNTUwMjE2/Mi01MTI1LmpwZWc.jpeg"
        },
        {
          "active": true,
          "id": 3690926,
          "name": "Sam Doores",
          "resource_url": "https://api.discogs.com/artists/3690926",
          "thumbnail_url": "https://i.discogs.com/lVo2vjOxNQ8LVa2rkFvML1FkU9DcAkIcG3NaKn5rijM/rs:fit/g:sm/q:40/h:400/w:600/czM6Ly9kaXNjb2dz/LWRhdGFiYXNlLWlt/YWdlcy9BLTM2OTA5/MjYtMTQzNTUwMjI5/NC04ODQ5LmpwZWc.jpeg"
        }
      ],
      "name": "Hurray For The Riff Raff",
      "namevariations": [
        "H.F.T.R.R.",
        "Hurrah For The Riff Raff"
      ],
      "profile": "Folk-blues/Americana band from New Orleans, Louisiana, USA founded in 2007.",
      "raw_data": {
        "data_quality": "Needs Vote",
        "id": 1819160,
        "images": [
          {
            "height": 474,
            "resource_url": "https://i.discogs.com/TwF5yCxBy57M5AyVtItus9VUCO3ncpCYa3uxvVGEYZk/rs:fit/g:sm/q:90/h:474/w:474/czM6Ly9kaXNjb2dz/LWRhdGFiYXNlLWlt/YWdlcy9BLTE4MTkx/NjAtMTYxOTYyODE1/OC0zODI5LmpwZWc.jpeg",
            "type": "primary",
            "uri": "https://i.discogs.com/TwF5yCxBy57M5AyVtItus9VUCO3ncpCYa3uxvVGEYZk/rs:fit/g:sm/q:90/h:474/w:474/czM6Ly9kaXNjb2dz/LWRhdGFiYXNlLWlt/YWdlcy9BLTE4MTkx/NjAtMTYxOTYyODE1/OC0zODI5LmpwZWc.jpeg",
            "uri150": "https://i.discogs.com/xaIwCbIQL75hJgXgdVZZiX1gtWGyZ8fLw-TSW3ddPwI/rs:fit/g:sm/q:40/h:150/w:150/czM6Ly9kaXNjb2dz/LWRhdGFiYXNlLWlt/YWdlcy9BLTE4MTkx/NjAtMTYxOTYyODE1/OC0zODI5LmpwZWc.jpeg",
            "width": 474
          },
          {
            "height": 267,
            "resource_url": "https://i.discogs.com/0bu4yie6F-1K4xhAcJ8hyIzn8STxvZCh5rgff5qdoxY/rs:fit/g:sm/q:90/h:267/w:490/czM6Ly9kaXNjb2dz/LWRhdGFiYXNlLWlt/YWdlcy9BLTE4MTkx/NjAtMTM5MTczMTYx/OC01NjE5LmpwZWc.jpeg",
            "type": "secondary",
            "uri": "https://i.discogs.com/0bu4yie6F-1K4xhAcJ8hyIzn8STxvZCh5rgff5qdoxY/rs:fit/g:sm/q:90/h:267/w:490/czM6Ly9kaXNjb2dz/LWRhdGFiYXNlLWlt/YWdlcy9BLTE4MTkx/NjAtMTM5MTczMTYx/OC01NjE5LmpwZWc.jpeg",
            "uri150": "https://i.discogs.com/f43mcVb9iPyyeE-6jtE6EZB5DHjYiU6vqGcXU6gm8ps/rs:fit/g:sm/q:40/h:150/w:150/czM6Ly9kaXNjb2dz/LWRhdGFiYXNlLWlt/YWdlcy9BLTE4MTkx/NjAtMTM5MTczMTYx/OC01NjE5LmpwZWc.jpeg",
            "width": 490
          },
          {
            "height": 626,
            "resource_url": "https://i.discogs.com/YlUaBR7auoJzwlnAy8Fhz3RcV-LAF58Mow8Q2wKktiw/rs:fit/g:sm/q:90/h:626/w:600/czM6Ly9kaXNjb2dz/LWRhdGFiYXNlLWlt/YWdlcy9BLTE4MTkx/NjAtMTYxOTYyODE1/Ni03MjY3LmpwZWc.jpeg",
            "type": "secondary",
            "uri": "https://i.discogs.com/YlUaBR7auoJzwlnAy8Fhz3RcV-LAF58Mow8Q2wKktiw/rs:fit/g:sm/q:90/h:626/w:600/czM6Ly9kaXNjb2dz/LWRhdGFiYXNlLWlt/YWdlcy9BLTE4MTkx/NjAtMTYxOTYyODE1/Ni03MjY3LmpwZWc.jpeg",
            "uri150": "https://i.discogs.com/bgjYABLgYYKNCEOz9L9QxWR5I-qKQBSlElQhP7d7f0o/rs:fit/g:sm/q:40/h:150/w:150/czM6Ly9kaXNjb2dz/LWRhdGFiYXNlLWlt/YWdlcy9BLTE4MTkx/NjAtMTYxOTYyODE1/Ni03MjY3LmpwZWc.jpeg",
            "width": 600
          },
          {
            "height": 600,
            "resource_url": "https://i.discogs.com/I5krxShFuwbOMZ4XKCxf0VsNKe_AIejMeSTdYgnocqA/rs:fit/g:sm/q:90/h:600/w:600/czM6Ly9kaXNjb2dz/LWRhdGFiYXNlLWlt/YWdlcy9BLTE4MTkx/NjAtMTYxOTYyODE1/OS05OTY0LmpwZWc.jpeg",
            "type": "secondary",
            "uri": "https://i.discogs.com/I5krxShFuwbOMZ4XKCxf0VsNKe_AIejMeSTdYgnocqA/rs:fit/g:sm/q:90/h:600/w:600/czM6Ly9kaXNjb2dz/LWRhdGFiYXNlLWlt/YWdlcy9BLTE4MTkx/NjAtMTYxOTYyODE1/OS05OTY0LmpwZWc.jpeg",
            "uri150": "https://i.discogs.com/5N7_g3ZkGGOK9e76PZOgQYMXjryJWOWsdMZ0n0JgyVg/rs:fit/g:sm/q:40/h:150/w:150/czM6Ly9kaXNjb2dz/LWRhdGFiYXNlLWlt/YWdlcy9BLTE4MTkx/NjAtMTYxOTYyODE1/OS05OTY0LmpwZWc.jpeg",
            "width": 600
          },
          {
            "height": 336,
            "resource_url": "https://i.discogs.com/7Lr6WXrOEFx4odBsxwTU9rFtmATvD84n1NIwXUj-9jk/rs:fit/g:sm/q:90/h:336/w:600/czM6Ly9kaXNjb2dz/LWRhdGFiYXNlLWlt/YWdlcy9BLTE4MTkx/NjAtMTYxOTYyODE2/MC0xNzk2LmpwZWc.jpeg",
            "type": "secondary",
            "uri": "https://i.discogs.com/7Lr6WXrOEFx4odBsxwTU9rFtmATvD84n1NIwXUj-9jk/rs:fit/g:sm/q:90/h:336/w:600/czM6Ly9kaXNjb2dz/LWRhdGFiYXNlLWlt/YWdlcy9BLTE4MTkx/NjAtMTYxOTYyODE2/MC0xNzk2LmpwZWc.jpeg",
            "uri150": "https://i.discogs.com/4Wvez4rZ5KR7Yej4vQV7AltsYpiqmMkkIDuqa9vbqoY/rs:fit/g:sm/q:40/h:150/w:150/czM6Ly9kaXNjb2dz/LWRhdGFiYXNlLWlt/YWdlcy9BLTE4MTkx/NjAtMTYxOTYyODE2/MC0xNzk2LmpwZWc.jpeg",
            "width": 600
          }
        ],
        "members": [
          {
            "active": false,
            "id": 1588103,
            "name": "Walt McClements",
            "resource_url": "https://api.discogs.com/artists/1588103",
            "thumbnail_url": ""
          },
          {
            "active": true,
            "id": 1984171,
            "name": "Dan Cutler",
            "resource_url": "https://api.discogs.com/artists/1984171",
            "thumbnail_url": "https://i.discogs.com/gB4edjl5ikO42sl5r85Ft5XLBcVPuEoGKOVX5HLog7o/rs:fit/g:sm/q:40/h:600/w:400/czM6Ly9kaXNjb2dz/LWRhdGFiYXNlLWlt/YWdlcy9BLTE5ODQx/NzEtMTQzNTUwMjQw/OC03MjU3LmpwZWc.jpeg"
          },
          {
            "active": true,
            "id": 2260277,
            "name": "Casey McAllister",
            "resource_url": "https://api.discogs.com/artists/2260277",
            "thumbnail_url": "https://i.discogs.com/6nuMggGQKKyUGmaynvuvjHV0LKJJB546Eq8dGj6nOxs/rs:fit/g:sm/q:40/h:399/w:600/czM6Ly9kaXNjb2dz/LWRhdGFiYXNlLWlt/YWdlcy9BLTIyNjAy/NzctMTU4ODg4MDk0/MS05NDg0LmpwZWc.jpeg"
          },
          {
            "active": true,
            "id": 2581847,
            "name": "Alynda Lee Segarra",
            "resource_url": "https://api.discogs.com/artists/2581847",
            "thumbnail_url": "https://i.discogs.com/SvzTL5QhEr5WIFQEhPpOW2YpahtnN-7y3Bm8h3K7qVY/rs:fit/g:sm/q:40/h:347/w:304/czM6Ly9kaXNjb2dz/LWRhdGFiYXNlLWlt/YWdlcy9BLTI1ODE4/NDctMTY1NDAxMDEz/OC03MDAxLmpwZWc.jpeg"
          },
          {
            "active": true,
            "id": 3690925,
            "name": "Yosi Perlstein",
            "resource_url": "https://api.discogs.com/artists/3690925",
            "thumbnail_url": "https://i.discogs.com/frqZRymcdFy4W8MRlbatCrCVfMACH9TomBvdWv-BqLQ/rs:fit/g:sm/q:40/h:400/w:600/czM6Ly9kaXNjb2dz/LWRhdGFiYXNlLWlt/YWdlcy9BLTM2OTA5/MjUtMTQzNTUwMjE2/Mi01MTI1LmpwZWc.jpeg"
          },
          {
            "active": true,
            "id": 3690926,
            "name": "Sam Doores",
            "resource_url": "https://api.discogs.com/artists/3690926",
            "thumbnail_url": "https://i.discogs.com/lVo2vjOxNQ8LVa2rkFvML1FkU9DcAkIcG3NaKn5rijM/rs:fit/g:sm/q:40/h:400/w:600/czM6Ly9kaXNjb2dz/LWRhdGFiYXNlLWlt/YWdlcy9BLTM2OTA5/MjYtMTQzNTUwMjI5/NC04ODQ5LmpwZWc.jpeg"
          }
        ],
        "name": "Hurray For The Riff Raff",
        "namevariations": [
          "H.F.T.R.R.",
          "Hurrah For The Riff Raff"
        ],
        "profile": "Folk-blues/Americana band from New Orleans, Louisiana, USA founded in 2007.",
        "releases_url": "https://api.discogs.com/artists/1819160/releases",
        "resource_url": "https://api.discogs.com/artists/1819160",
        "uri": "https://www.discogs.com/artist/1819160-Hurray-For-The-Riff-Raff",
        "urls": [
          "http://hurrayfortheriffraff.com/",
          "http://hftrr.bandcamp.com/",
          "http://www.facebook.com/hurrayfortheriffraff",
          "http://twitter.com/hftrr",
          "http://www.youtube.com/user/hurrayfortheriffraff",
          "https://en.wikipedia.org/wiki/Hurray_for_the_Riff_Raff"
        ]
      },
      "resource_url": "https://api.discogs.com/artists/1819160",
      "thumb": "https://i.discogs.com/xaIwCbIQL75hJgXgdVZZiX1gtWGyZ8fLw-TSW3ddPwI/rs:fit/g:sm/q:40/h:150/w:150/czM6Ly9kaXNjb2dz/LWRhdGFiYXNlLWlt/YWdlcy9BLTE4MTkx/NjAtMTYxOTYyODE1/OC0zODI5LmpwZWc.jpeg",
      "url": "https://www.discogs.com/artist/1819160-Hurray-For-The-Riff-Raff",
      "urls": [
        "http://hurrayfortheriffraff.com/",
        "http://hftrr.bandcamp.com/",
        "http://www.facebook.com/hurrayfortheriffraff",
        "http://twitter.com/hftrr",
        "http://www.youtube.com/user/hurrayfortheriffraff",
        "https://en.wikipedia.org/wiki/Hurray_for_the_Riff_Raff"
      ]
    },
    "lastfm": {
      "bio_content": "Hurray for the Riff Raff is an Americana band from New Orleans, Louisiana. It was formed by Alynda Segarra, a Puerto Rican singer-songwriter from the Bronx, New York, after they had moved to New Orleans in 2007.\n\nAfter leaving home at an early age to travel the country, Segarra eventually settled in New Orleans where they began to perform and record with a revolving cast of musicians.  They released two records (2008's It Don't Mean I Don't Love You and 2010's Young Blood Blues) mostly consisting of delicate folk and country songs.  In 2011, the UK record label Loose Music (Felice Brothers, Dawes, Deer Tick), released Hurray for the Riff Raff, an album that collected the best songs from those records.  The Times of London named Hurray for the Riff Raff one of the Top Ten Albums of 2011.  Phil Alexander, the Editor-in-Chief of Mojo Magazine, raved that they “have immense potential and seductive power” and named them second best band at SXSW 2011.\n\nBack in the States, Alynda met up with a young honky-tonk band called the Tumbleweeds, just as they began to expand they musical palette to include rock n roll, pop, and soul.  In the tradition of Bob Dylan with Band and Neil Young with Crazy Horse, Alynda recruited the Tumbleweeds to be their touring band, drastically altering the sound of Hurray for the Riff Raff.\n\nLook Out Mama is the result of almost two years of Alynda and the Tumbleweeds criss-crossing the USA, playing over 100 shows in small bars and clubs.  Recorded in Nashville by producer Andrija Tokic (Alabama Shakes), Look Out Mama is an exploration of classic American music as interpreted by Alynda lee Segarra.  From the Swamp Pop of \"Little Black Star\" to the Classic Country of \"Look Out Mama\", to the Psychedelia of “Ode to John and Yoko” and even the Surf-Rock of “Lake of Fire”, Look Out Mama covers a wide array of musical ground, with every song unified by Alynda’s soulful vocals and expert songwriting. <a href=\"https://www.last.fm/music/Hurray+For+The+Riff+Raff\">Read more on Last.fm</a>. User-contributed text is available under the Creative Commons By-SA License; additional terms may apply.",
      "bio_summary": "Hurray for the Riff Raff is an Americana band from New Orleans, Louisiana. It was formed by Alynda Segarra, a Puerto Rican singer-songwriter from the Bronx, New York, after they had moved to New Orleans in 2007.\n\nAfter leaving home at an early age to travel the country, Segarra eventually settled in New Orleans where they began to perform and record with a revolving cast of musicians.  They released two records (2008's It Don't Mean I Don't Love You and 2010's Young Blood Blues) mostly consisting of delicate folk and country songs. <a href=\"https://www.last.fm/music/Hurray+For+The+Riff+Raff\">Read more on Last.fm</a>",
      "images": [
        {
          "size": "small",
          "url": "https://lastfm.freetls.fastly.net/i/u/34s/2a96cbd8b46e442fc41c2b86b821562f.png"
        },
        {
          "size": "medium",
          "url": "https://lastfm.freetls.fastly.net/i/u/64s/2a96cbd8b46e442fc41c2b86b821562f.png"
        },
        {
          "size": "large",
          "url": "https://lastfm.freetls.fastly.net/i/u/174s/2a96cbd8b46e442fc41c2b86b821562f.png"
        },
        {
          "size": "extralarge",
          "url": "https://lastfm.freetls.fastly.net/i/u/300x300/2a96cbd8b46e442fc41c2b86b821562f.png"
        },
        {
          "size": "mega",
          "url": "https://lastfm.freetls.fastly.net/i/u/300x300/2a96cbd8b46e442fc41c2b86b821562f.png"
        },
        {
          "size": "",
          "url": "https://lastfm.freetls.fastly.net/i/u/300x300/2a96cbd8b46e442fc41c2b86b821562f.png"
        }
      ],
      "listeners": 219282,
      "mbid": "b053efc9-e8ea-474a-981f-a3c6fffcc694",
      "name": "Hurray For The Riff Raff",
      "playcount": 3640947,
      "similar_artists": [
        {
          "name": "TORRES",
          "url": "https://www.last.fm/music/TORRES"
        },
        {
          "name": "Jess Williamson",
          "url": "https://www.last.fm/music/Jess+Williamson"
        },
        {
          "name": "Julie Byrne",
          "url": "https://www.last.fm/music/Julie+Byrne"
        },
        {
          "name": "Madi Diaz",
          "url": "https://www.last.fm/music/Madi+Diaz"
        },
        {
          "name": "Bonny Light Horseman",
          "url": "https://www.last.fm/music/Bonny+Light+Horseman"
        }
      ],
      "tags": [
        "folk",
        "americana",
        "blues",
        "seen live",
        "New Orleans"
      ],
      "url": "https://www.last.fm/music/Hurray+For+The+Riff+Raff"
    },
    "spotify": {
      "followers": 142231,
      "genres": [
        "americana",
        "alt country"
      ],
      "id": "2xLEV2jDreAOcpJXFNoXyt",
      "images": [
        {
          "height": 640,
          "url": "https://i.scdn.co/image/ab6761610000e5eb057068ad79970a943dc50686",
          "width": 640
        },
        {
          "height": 320,
          "url": "https://i.scdn.co/image/ab67616100005174057068ad79970a943dc50686",
          "width": 320
        },
        {
          "height": 160,
          "url": "https://i.scdn.co/image/ab6761610000f178057068ad79970a943dc50686",
          "width": 160
        }
      ],
      "name": "Hurray For The Riff Raff",
      "popularity": 49,
      "url": "https://open.spotify.com/artist/2xLEV2jDreAOcpJXFNoXyt"
    }
  },
  "spotify_id": "2xLEV2jDreAOcpJXFNoXyt",
  "spotify_url": "https://open.spotify.com/artist/2xLEV2jDreAOcpJXFNoXyt",
  "updated_at": "2025-07-08T10:07:46.271958",
  "wikipedia_url": null
}